Translation/__init__.py
Translation/translator.py
translatifyhone-0.4.dist-info/METADATA
translatifyhone-0.4.dist-info/WHEEL
translatifyhone-0.4.dist-info/top_level.txt
translatifyhone-0.4.dist-info/RECORD
